pyltd2/__init__.py
pyltd2/_constants.py
pyltd2/exceptions.py
pyltd2/fetcher.py
pyltd2/logger.py
pyltd2/offset_iterator.py
pyltd2/utils.py
pyltd2-1.0.1rc0.dist-info/LICENSE
pyltd2-1.0.1rc0.dist-info/WHEEL
pyltd2-1.0.1rc0.dist-info/METADATA
pyltd2-1.0.1rc0.dist-info/RECORD
