Metadata-Version: 2.1
Name: pyltd2
Version: 1.0.1rc0
Summary: Client package for the download of Legion TD 2 game data.
Home-page: https://github.com/GCidd/pyltd2
License: MIT
Keywords: api,Legion td 2,fetch,call
Author: GCidd
Requires-Python: >=3.8,<4.0
Classifier: Intended Audience :: Developers
Classifier: License :: OSI Approved :: MIT License
Classifier: Operating System :: MacOS
Classifier: Operating System :: Microsoft
Classifier: Operating System :: POSIX :: Linux
Classifier: Programming Language :: Python
Classifier: Programming Language :: Python :: 3
Classifier: Programming Language :: Python :: 3.10
Classifier: Programming Language :: Python :: 3.8
Classifier: Programming Language :: Python :: 3.9
Classifier: Topic :: Software Development
Classifier: Topic :: Utilities
Requires-Dist: numpy (>=1.16.5,<2.0.0)
Requires-Dist: pandas (>=1.2.0,<2.0.0)
Requires-Dist: requests (>=2.1.0,<3.0.0)
Requires-Dist: tqdm (>=4.64.0,<5.0.0)
Project-URL: Repository, https://github.com/GCidd/pyltd2
